<?xml version="1.0" encoding="utf-8"?>
<CraftingPieces>

   <CraftingPiece id="bk_jav_double_menavlon" name="{=!}Double Menavlon Javelin Heads" tier="3" piece_type="Blade" mesh="spear_blade_14" length="46.28" weight="0.5268" 
				  excluded_item_usage_features="swing:TwoHandedPolearm_Bracing">
		<BladeData stack_amount="5" physics_material="wood_weapon" body_name="bo_spear_b" holster_mesh="no_jav_quiver" holster_body_name="bo_throwing_spear_quiver_4" holster_mesh_length="96.2">
			<Thrust damage_type="Pierce" damage_factor="0.9" />
		</BladeData>
		<Materials>
			<Material id="Iron3" count="1" />
		</Materials>
	</CraftingPiece>
	
	<CraftingPiece
		id="bk_2h_mahogany"
		name="{=!}Extra Long Two-Handed Mahogany Shaft"
		tier="4"
		piece_type="Handle"
		mesh="spear_handle_27"
		length="290"
		weight="1.6"
		is_default="true">
		<BuildData
			piece_offset="22.9" />
		<Materials>
			<Material
				id="Wood"
				count="1" />
		</Materials>
	</CraftingPiece>
	
	<CraftingPiece
		id="kanic_blade_1"
		name="{=!}Pointy Xyphos Blade"
		tier="4"
		piece_type="Blade"
		mesh="dagger_blade_7"
		length="40"
		weight="0.325">
		<BladeData
			stack_amount="3"
			physics_material="metal_weapon"
			body_name="bo_sword_one_handed"
			holster_mesh="">
			<Thrust
				damage_type="Pierce"
				damage_factor="2.7" />
			<Swing
				damage_type="Cut"
				damage_factor="3.9" />
		</BladeData>
		<Flags>
			<Flag
				name="Civilian"
				type="ItemFlags" />
		</Flags>
		<Materials>
			<Material
				id="Iron5"
				count="3" />
		</Materials>
	</CraftingPiece>
	
	<CraftingPiece
		id="kanic_blade_2"
		name="{=!}Xyphos Blade"
		tier="3"
		piece_type="Blade"
		mesh="dagger_blade_11"
		length="30"
		weight="0.475">
		<BladeData
			stack_amount="3"
			physics_material="metal_weapon"
			body_name="bo_sword_one_handed"
			holster_mesh="">
			<Thrust
				damage_type="Pierce"
				damage_factor="2.2" />
			<Swing
				damage_type="Cut"
				damage_factor="3.6" />
		</BladeData>
		<Flags>
			<Flag
				name="Civilian"
				type="ItemFlags" />
		</Flags>
		<Materials>
			<Material
				id="Iron3"
				count="3" />
		</Materials>
	</CraftingPiece>
	
	<!-- #endregion pila and throwing spears -->
	<CraftingPiece id="spear_blade_13" name="{=MpVC0RXl}Northern Triangular Spear" tier="5" piece_type="Blade" mesh="spear_blade_13" length="50.864" weight="0.4592" excluded_item_usage_features="swing">
		<BladeData stack_amount="2" physics_material="wood_weapon" body_name="bo_spear_b" holster_mesh="no_jav_quiver" holster_body_name="bo_throwing_spear_quiver_5_1" holster_mesh_length="96.7">
			<Thrust damage_type="Pierce" damage_factor="1.1" />
		</BladeData>
		<Flags>
		</Flags>
		<Materials>
			<Material id="Iron5" count="2" />
		</Materials>
	</CraftingPiece>
	<CraftingPiece id="spear_blade_35" name="{=ZUp9mm79}Jagged Spear Head" tier="5" piece_type="Blade" mesh="spear_blade_35" length="41" weight="0.3256" excluded_item_usage_features="swing">
		<BladeData stack_amount="2" physics_material="wood_weapon" body_name="bo_spear_b" holster_mesh="no_jav_quiver" holster_body_name="bo_throwing_spear_quiver_5_1" holster_mesh_length="96.7">
			<Thrust damage_type="Pierce" damage_factor="1.1" />
		</BladeData>
		<Flags>
		</Flags>
		<Materials>
			<Material id="Iron3" count="3" />
		</Materials>
	</CraftingPiece>

	<CraftingPiece id="spear_blade_35_blunt" name="{=ZUp9mm79}Jagged Spear Head" tier="5" piece_type="Blade" mesh="spear_blade_35" length="41" weight="0.3256" excluded_item_usage_features="swing">
		<BladeData stack_amount="2" physics_material="wood_weapon" body_name="bo_spear_b" holster_mesh="no_jav_quiver" holster_body_name="bo_throwing_spear_quiver_5_1" holster_mesh_length="96.7">
			<Thrust damage_type="Pierce" damage_factor="1.1" />
		</BladeData>
		<Flags>
		</Flags>
		<Materials>
			<Material id="Iron3" count="3" />
		</Materials>
	</CraftingPiece>

	<CraftingPiece id="spear_blade_38" name="{=nr3K4od2}Pilum Head" tier="5" piece_type="Blade" mesh="spear_blade_38" length="23.7" weight="0.250" excluded_item_usage_features="swing">
		<BladeData stack_amount="2" physics_material="wood_weapon" body_name="bo_spear_b" holster_mesh="no_jav_quiver" holster_body_name="bo_throwing_spear_quiver_3_2" holster_mesh_length="96.8">
			<Thrust damage_type="Pierce" damage_factor="1.2" />
		</BladeData>
		<Flags>
			<Flag name="BonusAgainstShield" />
		</Flags>
		<Materials>
			<Material id="Iron3" count="1" />
		</Materials>
	</CraftingPiece>
	<!-- #endregion cut polearms -->
	<CraftingPiece id="spear_blade_43" name="{=wait0O6m}Warrazor Head" tier="5" piece_type="Blade" mesh="spear_blade_43" length="64.4" weight="0.6" excluded_item_usage_features="shield">
		<BladeData stack_amount="3" physics_material="wood_weapon" body_name="bo_spear_b">
			<Thrust damage_type="Pierce" damage_factor="0.4" />
			<Swing damage_type="Cut" damage_factor="1.3" />
		</BladeData>
		<Materials>
			<Material id="Iron4" count="2" />
		</Materials>
	</CraftingPiece>

	<CraftingPiece id="spear_blade_7" name="{=dXRt8jY4}Menavlion Head" tier="5" piece_type="Blade" mesh="spear_blade_7" length="30" weight="0.3656" excluded_item_usage_features="swing">
		<BladeData stack_amount="3" physics_material="wood_weapon" body_name="bo_spear_b">
			<Thrust damage_type="Pierce" damage_factor="1.3" />
		</BladeData>
		<Materials>
			<Material id="Iron4" count="1" />
		</Materials>
	</CraftingPiece>

	<CraftingPiece id="spear_blade_18" name="{=qSV6C2tp}Swordstaff Head" tier="5" piece_type="Blade" mesh="spear_blade_18" length="45" weight="0.4096" excluded_item_usage_features="swing">
		<BladeData stack_amount="3" physics_material="wood_weapon" body_name="bo_spear_b">
			<Thrust damage_type="Pierce" damage_factor="1.35" />
		</BladeData>
		<Materials>
			<Material id="Iron4" count="2" />
		</Materials>
	</CraftingPiece>

	<CraftingPiece id="spear_blade_19" name="{=OBeOZ27b}Glaive Head" tier="5" piece_type="Blade" mesh="spear_blade_19" length="37.4" weight="0.35">
		<BladeData stack_amount="3" physics_material="wood_weapon" body_name="bo_spear_b">
			<Thrust damage_type="Pierce" damage_factor="0.4" />
			<Swing damage_type="Cut" damage_factor="1.1" />
		</BladeData>
		<Materials>
			<Material id="Iron4" count="1" />
		</Materials>
	</CraftingPiece>

	<CraftingPiece id="spear_blade_19_blunt" name="{=OBeOZ27b}Glaive Head" tier="5" piece_type="Blade" mesh="spear_blade_19" length="37.4" weight="0.3">
		<BladeData stack_amount="3" physics_material="wood_weapon" body_name="bo_spear_b">
			<Thrust damage_type="Pierce" damage_factor="0.4" />
			<Swing damage_type="Cut" damage_factor="1.1" />
		</BladeData>
		<Materials>
			<Material id="Iron4" count="1" />
		</Materials>
	</CraftingPiece>

	<CraftingPiece id="spear_blade_24" name="{=bjQ8J71a}Long Glaive Head" tier="5" piece_type="Blade" mesh="spear_blade_24" length="68" weight="0.40">
		<BladeData stack_amount="3" physics_material="wood_weapon" body_name="bo_spear_b">
			<Thrust damage_type="Pierce" damage_factor="0.5" />
			<Swing damage_type="Cut" damage_factor="1.2" />
		</BladeData>
		<Materials>
			<Material id="Iron5" count="2" />
		</Materials>
	</CraftingPiece>

	<CraftingPiece id="axe_craft_10_head" name="{=LNDbMUK0}Voulge Head" tier="5" piece_type="Blade" mesh="axe_craft_10_head" distance_to_next_piece="23" distance_to_previous_piece="4" weight="0.6">
		<BuildData piece_offset="-8" />
		<BladeData stack_amount="3" blade_length="23.118" blade_width="18.371" physics_material="metal_weapon" body_name="bo_axe_longer_b">
			<Thrust damage_type="Pierce" damage_factor="0.8" />
			<Swing damage_type="Cut" damage_factor="1.2" />
		</BladeData>
		<Flags>
			<Flag name="CanBePickedUpFromCorpse" type="ItemFlags" />
		</Flags>
		<Materials>
			<Material id="Iron5" count="2" />
		</Materials>
	</CraftingPiece>

	<CraftingPiece id="spear_blade_33" name="{=R62maL2H}Bill Head" tier="2" piece_type="Blade" mesh="spear_blade_33" length="35.5" weight="0.3296" excluded_item_usage_features="shield:thrust">
		<BladeData stack_amount="3" physics_material="wood_weapon" body_name="bo_spear_b">
			<Swing damage_type="Cut" damage_factor="0.5" />
		</BladeData>
		<Materials>
			<Material id="Iron2" count="1" />
		</Materials>
	</CraftingPiece>

	<CraftingPiece id="spear_blade_33_blunt" name="{=R62maL2H}Bill Head" tier="2" piece_type="Blade" mesh="spear_blade_33" length="35.5" weight="0.3296" excluded_item_usage_features="shield:thrust">
		<BladeData stack_amount="3" physics_material="wood_weapon" body_name="bo_spear_b">
			<Swing damage_type="Cut" damage_factor="0.5" />
		</BladeData>
		<Materials>
			<Material id="Iron2" count="1" />
		</Materials>
	</CraftingPiece>

	<CraftingPiece id="battania_blade_7" name="{=1Ia3Wxbf}Fine Steel Falx Blade" tier="5" piece_type="Blade" mesh="battania_blade_7" culture="Culture.battania" length="75" weight="0.6" excluded_item_usage_features="shield:thrust">
		<BladeData stack_amount="3" physics_material="metal_weapon" body_name="bo_sword_one_handed">
			<Swing damage_type="Cut" damage_factor="1.2" />
		</BladeData>
		<Flags>
			<Flag name="BonusAgainstShield" />
		</Flags>
		<Materials>
			<Material id="Iron6" count="2" />
		</Materials>
	</CraftingPiece>

	<CraftingPiece id="spear_blade_22" name="{=3ged5Ozt}Exceptional Eastern Glaive" tier="5" piece_type="Blade" mesh="spear_blade_22" length="89" weight="0.4">
		<BladeData stack_amount="3" physics_material="wood_weapon" body_name="bo_spear_b">
			<Thrust damage_type="Pierce" damage_factor="0.55" />
			<Swing damage_type="Cut" damage_factor="1.3" />
		</BladeData>
		<Materials>
			<Material id="Iron5" count="2" />
		</Materials>
	</CraftingPiece>

	<CraftingPiece id="spear_blade_44" name="{=PmPxx2gK}Bent Razor Head" tier="1" piece_type="Blade" mesh="spear_blade_44" length="80" weight="0.33" excluded_item_usage_features="">
		<BladeData stack_amount="3" physics_material="wood_weapon" body_name="bo_spear_b">
			<Thrust damage_type="Pierce" damage_factor="0.4" />
			<Swing damage_type="Cut" damage_factor="0.6" />
		</BladeData>
		<Materials>
			<Material id="Iron4" count="2" />
		</Materials>
	</CraftingPiece>

	<!-- #unused ATM -->
	<CraftingPiece id="spear_blade_45" name="{=LNDbMUK0}Voulge Head" tier="4" piece_type="Blade" mesh="spear_blade_45" length="40" weight="1.2" excluded_item_usage_features="">
		<BladeData stack_amount="3" physics_material="wood_weapon" body_name="bo_spear_b">
			<Thrust damage_type="Pierce" damage_factor="0.7" />
			<Swing damage_type="Cut" damage_factor="0.9" />
		</BladeData>
		<Materials>
			<Material id="Iron4" count="2" />
		</Materials>
	</CraftingPiece>

	<!-- #region Used Lance Blade Pieces -->

	<CraftingPiece id="spear_blade_23" name="{=OryiZr9d}Light Lance Head" tier="5" piece_type="Blade" mesh="spear_blade_23" length="42" weight="0.1" excluded_item_usage_features="swing">
		<BladeData stack_amount="3" physics_material="wood_weapon" body_name="bo_spear_b">
			<Thrust damage_type="Pierce" damage_factor="1.3" />
		</BladeData>
		<Materials>
			<Material id="Iron3" count="2" />
		</Materials>
		<Flags>
		</Flags>
	</CraftingPiece>

	<CraftingPiece id="spear_blade_23_blunt" name="{=OryiZr9d}Tournament Light Lance Head" tier="5" piece_type="Blade" mesh="spear_blade_23" length="42" weight="0.1" excluded_item_usage_features="swing">
		<BladeData stack_amount="3" physics_material="wood_weapon" body_name="bo_spear_b">
			<Thrust damage_type="Pierce" damage_factor="1.3" />
		</BladeData>
		<Materials>
			<Material id="Iron3" count="2" />
		</Materials>
		<Flags>
		</Flags>
	</CraftingPiece>

	<CraftingPiece id="spear_blade_20" name="{=uwG8iwBc}Medium Lance Head" tier="5" piece_type="Blade" mesh="spear_blade_20" length="46" weight="0.1" excluded_item_usage_features="swing">
		<BladeData stack_amount="3" physics_material="wood_weapon" body_name="bo_spear_b">
			<Thrust damage_type="Pierce" damage_factor="1.35" />
		</BladeData>
		<Materials>
			<Material id="Iron4" count="1" />
		</Materials>
		<Flags>
		</Flags>
	</CraftingPiece>

	<CraftingPiece id="spear_blade_20_blunt" name="{=uwG8iwBc}Tournament Medium Lance Head" tier="5" piece_type="Blade" mesh="spear_blade_20" length="46" weight="0.1" excluded_item_usage_features="swing">
		<BladeData stack_amount="3" physics_material="wood_weapon" body_name="bo_spear_b">
			<Thrust damage_type="Pierce" damage_factor="1.35" />
		</BladeData>
		<Materials>
			<Material id="Iron4" count="1" />
		</Materials>
		<Flags>
		</Flags>
	</CraftingPiece>

	<CraftingPiece id="spear_blade_5" name="{=QwfDN06p}Heavy Lance Head" tier="5" piece_type="Blade" mesh="spear_blade_5" length="52.242" weight="0.1" excluded_item_usage_features="swing">
		<BladeData stack_amount="3" physics_material="wood_weapon" body_name="bo_spear_b">
			<Thrust damage_type="Pierce" damage_factor="1.4" />
		</BladeData>
		<Materials>
			<Material id="Iron5" count="1" />
		</Materials>
		<Flags>
		</Flags>
	</CraftingPiece>

	<!-- #region Used Spear Blade Pieces -->

	<CraftingPiece id="spear_blade_6" name="{=S75vUGzK}Fine Steel Hewing Spear Head" tier="5" piece_type="Blade" mesh="spear_blade_6" length="84.4" weight="1.25">
		<BladeData stack_amount="3" physics_material="wood_weapon" body_name="bo_spear_b">
			<Thrust damage_type="Pierce" damage_factor="1.15" />
			<Swing damage_type="Cut" damage_factor="0.9" />
		</BladeData>
		<Materials>
			<Material id="Iron5" count="1" />
		</Materials>
	</CraftingPiece>

	<CraftingPiece id="spear_blade_1" name="{=Oxew9WCe}Imperial Simple Spear Head" tier="2" piece_type="Blade" mesh="spear_blade_1" length="48" weight="0.36" excluded_item_usage_features="swing">
		<BladeData stack_amount="5" physics_material="wood_weapon" body_name="bo_spear_b" holster_mesh="no_jav_quiver" holster_body_name="bo_throwing_spear_quiver_4" holster_mesh_length="96.2">
			<Thrust damage_type="Pierce" damage_factor="0.8" />
		</BladeData>
		<Materials>
			<Material id="Iron2" count="1" />
		</Materials>
	</CraftingPiece>

	<CraftingPiece id="spear_blade_8" name="{=CdBAvJdP}Kontos Head" tier="3" piece_type="Blade" mesh="spear_blade_8" length="60.153" weight="0.4" excluded_item_usage_features="swing">
		<BladeData stack_amount="3" physics_material="wood_weapon" body_name="bo_spear_b">
			<Thrust damage_type="Pierce" damage_factor="0.9" />
		</BladeData>
		<Materials>
			<Material id="Iron3" count="2" />
		</Materials>
	</CraftingPiece>

	<CraftingPiece id="spear_blade_4" name="{=ZcUNAfKT}Extra Long Fine Steel Spear Head" tier="4" piece_type="Blade" mesh="spear_blade_4" length="72.558" weight="0.5168" excluded_item_usage_features="swing">
		<BladeData stack_amount="3" physics_material="wood_weapon" body_name="bo_spear_b">
			<Thrust damage_type="Pierce" damage_factor="1" />
		</BladeData>
		<Materials>
			<Material id="Iron4" count="2" />
		</Materials>
	</CraftingPiece>

	<CraftingPiece id="spear_blade_42" name="{=9aYBy1RN}Fine Steel Leaf Spear Head" tier="4" piece_type="Blade" mesh="spear_blade_42" length="42" weight="0.5456" excluded_item_usage_features="swing">
		<BladeData stack_amount="3" physics_material="wood_weapon" body_name="bo_spear_b" holster_mesh="no_jav_quiver" holster_body_name="bo_throwing_spear_quiver_4_1" holster_mesh_length="96.2">
			<Thrust damage_type="Pierce" damage_factor="1" />
		</BladeData>
		<Materials>
			<Material id="Iron4" count="2" />
		</Materials>
	</CraftingPiece>

	<CraftingPiece id="spear_blade_14" name="{=T1aiDuOp}Narrow Menavlon Head" tier="3" piece_type="Blade" mesh="spear_blade_14" length="46.28" weight="0.5268" excluded_item_usage_features="swing:TwoHandedPolearm_Bracing">
		<BladeData stack_amount="5" physics_material="wood_weapon" body_name="bo_spear_b" holster_mesh="no_jav_quiver" holster_body_name="bo_throwing_spear_quiver_4" holster_mesh_length="96.2">
			<Thrust damage_type="Pierce" damage_factor="0.9" />
		</BladeData>
		<Materials>
			<Material id="Iron3" count="1" />
		</Materials>
	</CraftingPiece>

	<CraftingPiece id="spear_blade_37" name="{=XSabsFbx}Weighted Awl Pike Head" tier="3" piece_type="Blade" mesh="spear_blade_37" length="23.7" weight="0.4104" excluded_item_usage_features="swing">
		<BladeData stack_amount="5" physics_material="wood_weapon" body_name="bo_spear_b" holster_mesh="no_jav_quiver" holster_body_name="bo_throwing_spear_quiver_5" holster_mesh_length="96.7">
			<Thrust damage_type="Pierce" damage_factor="0.9" />
		</BladeData>
		<Materials>
			<Material id="Iron3" count="2" />
		</Materials>
	</CraftingPiece>

	<CraftingPiece id="spear_blade_27" name="{=1rGNXUaJ}Thin Fine Steel Hewing Spear Head" tier="5" piece_type="Blade" mesh="spear_blade_27" length="69.5" weight="0.7">
		<BladeData stack_amount="4" physics_material="wood_weapon" body_name="bo_spear_b" holster_mesh="no_jav_quiver" holster_body_name="bo_throwing_spear_quiver_2" holster_mesh_length="94.6">
			<Thrust damage_type="Pierce" damage_factor="1.25" />
			<Swing damage_type="Cut" damage_factor="1.0" />
		</BladeData>
		<Materials>
			<Material id="Iron5" count="2" />
		</Materials>
	</CraftingPiece>

	<CraftingPiece id="spear_blade_40" name="{=NAHHwS3G}Broad Leaf Shaped Spear Tip" tier="3" piece_type="Blade" mesh="spear_blade_40" length="42" weight="1">
		<BladeData stack_amount="3" physics_material="wood_weapon" body_name="bo_spear_b">
			<Thrust damage_type="Pierce" damage_factor="0.85" />
			<Swing damage_type="Cut" damage_factor="0.7" />
		</BladeData>
		<Materials>
			<Material id="Iron3" count="2" />
		</Materials>
	</CraftingPiece>

	<CraftingPiece id="spear_blade_36" name="{=nRKOX66b}Jagged Fine Steel Spear Head" tier="4" piece_type="Blade" mesh="spear_blade_36" length="42.5" weight="0.468" excluded_item_usage_features="swing">
		<BladeData stack_amount="3" physics_material="wood_weapon" body_name="bo_spear_b">
			<Thrust damage_type="Pierce" damage_factor="1" />
		</BladeData>
		<Materials>
			<Material id="Iron4" count="2" />
		</Materials>
	</CraftingPiece>
	<!-- Javelin -->
	<CraftingPiece id="spear_blade_15" name="{=Y4tIQnS4}Short Simple Spear Head" tier="2" piece_type="Blade" mesh="spear_blade_15" length="22.862" weight="0.300" excluded_item_usage_features="swing">
		<BladeData stack_amount="5" physics_material="wood_weapon" body_name="bo_spear_b" holster_mesh="no_jav_quiver" holster_body_name="bo_throwing_spear_quiver_1_1" holster_mesh_length="68.9">
			<Thrust damage_type="Pierce" damage_factor="0.8" />
		</BladeData>
		<Materials>
			<Material id="Iron2" count="1" />
		</Materials>
	</CraftingPiece>
	<!-- Javelin -->
	<CraftingPiece id="spear_blade_15_blunt" name="{=Y4tIQnS4}Short Simple Spear Head" tier="2" piece_type="Blade" mesh="spear_blade_15" length="22.862" weight="0.300" excluded_item_usage_features="swing">
		<BladeData stack_amount="4" physics_material="wood_weapon" body_name="bo_spear_b" holster_mesh="no_jav_quiver" holster_body_name="bo_throwing_spear_quiver_1_1" holster_mesh_length="68.9">
			<Thrust damage_type="Pierce" damage_factor="0.8" />
		</BladeData>
		<Materials>
			<Material id="Iron2" count="1" />
		</Materials>
	</CraftingPiece>
	<!-- Pike -->
	<CraftingPiece id="spear_blade_41" name="{=TKVxb6QD}Thamaskene Steel Leaf Shaped Pike Head" tier="5" piece_type="Blade" mesh="spear_blade_41" length="53.2" weight="0.4792" excluded_item_usage_features="swing">
		<BladeData stack_amount="1" physics_material="wood_weapon" body_name="bo_spear_b">
			<Thrust damage_type="Pierce" damage_factor="1.2" />
		</BladeData>
		<Materials>
			<Material id="Iron5" count="2" />
		</Materials>
	</CraftingPiece>
	<!-- Pike -->
	<CraftingPiece id="spear_blade_10" name="{=emUoygLE}Harpoon Head" tier="2" piece_type="Blade" mesh="spear_blade_10" length="39.775" weight="0.54" excluded_item_usage_features="swing">
		<BladeData stack_amount="5" physics_material="wood_weapon" body_name="bo_spear_b" holster_mesh="no_jav_quiver" holster_body_name="bo_throwing_spear_quiver_1" holster_mesh_length="68.9">
			<Thrust damage_type="Pierce" damage_factor="0.8" />
		</BladeData>
		<Materials>
			<Material id="Iron3" count="1" />
		</Materials>
	</CraftingPiece>

	<CraftingPiece id="spear_blade_16" name="{=Js1FKwrL}Javelin Head" tier="3" piece_type="Blade" mesh="spear_blade_16" length="23.328" weight="0.450" excluded_item_usage_features="swing">
		<BladeData stack_amount="4" physics_material="wood_weapon" body_name="bo_spear_b" holster_mesh="no_jav_quiver" holster_body_name="bo_throwing_spear_quiver_3_1" holster_mesh_length="96.8">
			<Thrust damage_type="Pierce" damage_factor="0.9" />
		</BladeData>
		<Materials>
			<Material id="Iron2" count="1" />
		</Materials>
	</CraftingPiece>

	<CraftingPiece id="spear_blade_11" name="{=S9zZO7qJ}Fine Steel Pike Head" tier="4" piece_type="Blade" mesh="spear_blade_11" length="34.56" weight="0.5096" excluded_item_usage_features="swing">
		<BladeData stack_amount="3" physics_material="wood_weapon" body_name="bo_spear_b">
			<Thrust damage_type="Pierce" damage_factor="1" />
		</BladeData>
		<Materials>
			<Material id="Iron4" count="1" />
		</Materials>
	</CraftingPiece>

	<CraftingPiece id="spear_blade_9" name="{=r3R6RM9G}Short Simple Pike Head" tier="1" piece_type="Blade" mesh="spear_blade_9" length="23.328" weight="0.404" excluded_item_usage_features="swing" is_default="true">
		<BladeData stack_amount="3" physics_material="wood_weapon" body_name="bo_spear_b" holster_mesh="no_jav_quiver" holster_body_name="bo_throwing_spear_quiver_3_1" holster_mesh_length="96.8">
			<Thrust damage_type="Pierce" damage_factor="0.75" />
		</BladeData>
		<Materials>
			<Material id="Iron2" count="1" />
		</Materials>
	</CraftingPiece>

	<CraftingPiece id="spear_blade_3" name="{=ZAoWK9Gt}Rounded Imperial Spear Head" tier="2" piece_type="Blade" mesh="spear_blade_3" length="57.143" weight="0.5536" excluded_item_usage_features="swing">
		<BladeData stack_amount="3" physics_material="wood_weapon" body_name="bo_spear_b">
			<Thrust damage_type="Pierce" damage_factor="0.8" />
		</BladeData>
		<Materials>
			<Material id="Iron2" count="1" />
		</Materials>
	</CraftingPiece>

	<CraftingPiece id="spear_blade_26" name="{=Y0gbKTgZ}Sturgian Military Fork Head" tier="2" piece_type="Blade" mesh="spear_blade_26" length="29.8" weight="0.5584" excluded_item_usage_features="swing">
		<BladeData stack_amount="3" physics_material="wood_weapon" body_name="bo_spear_b">
			<Thrust damage_type="Pierce" damage_factor="0.8" />
		</BladeData>
		<Flags></Flags>
		<Materials>
			<Material id="Iron2" count="2" />
		</Materials>
	</CraftingPiece>

	<CraftingPiece id="spear_blade_2" name="{=U30HpvtI}Triangular Iron Northern Spear Head" tier="3" piece_type="Blade" mesh="spear_blade_2" length="47.843" weight="0.4912" excluded_item_usage_features="swing">
		<BladeData stack_amount="3" physics_material="wood_weapon" body_name="bo_spear_b">
			<Thrust damage_type="Pierce" damage_factor="0.9" />
		</BladeData>
		<Materials>
			<Material id="Iron3" count="2" />
		</Materials>
	</CraftingPiece>

	<CraftingPiece id="spear_blade_39" name="{=8T7gNbfM}Drilled Wide Leaf Shaped Spear Head" tier="4" piece_type="Blade" mesh="spear_blade_39" length="54.2" weight="0.5216" excluded_item_usage_features="swing">
		<BladeData stack_amount="3" physics_material="wood_weapon" body_name="bo_spear_b">
			<Thrust damage_type="Pierce" damage_factor="1" />
		</BladeData>
		<Materials>
			<Material id="Iron4" count="2" />
		</Materials>
	</CraftingPiece>

	<CraftingPiece id="spear_blade_25" name="{=mrTkURKV}Notched Fork Head" tier="3" piece_type="Blade" mesh="spear_blade_25" length="42.5" weight="0.5504" excluded_item_usage_features="swing">
		<BladeData stack_amount="3" physics_material="wood_weapon" body_name="bo_spear_b">
			<Thrust damage_type="Pierce" damage_factor="0.9" />
		</BladeData>
		<Flags></Flags>
		<Materials>
			<Material id="Iron3" count="2" />
		</Materials>
	</CraftingPiece>
	<!-- #endregion cut polearms -->

	<!-- Spear Blades -->
	<CraftingPiece id="AR_spear_blade_a" name="{=osa_ar_spear_blade_a}Spiculum Head" tier="5" piece_type="Blade" mesh="AR_spear_blade_a" length="23.7" weight="0.250" excluded_item_usage_features="swing">
		<BladeData stack_amount="2" physics_material="wood_weapon" body_name="bo_spear_b" holster_mesh="no_jav_quiver" holster_body_name="bo_throwing_spear_quiver_5" holster_mesh_length="96.8">
			<Thrust damage_type="Pierce" damage_factor="1.5"/>
		</BladeData>
		<Flags>
			<Flag name="BonusAgainstShield"/>
		</Flags>
		<Materials>
			<Material id="Iron3" count="1"/>
		</Materials>
	</CraftingPiece>
	<CraftingPiece id="AR_spear_blade_b" name="{=osa_ar_spear_blade_b}Heavy Angon Head" tier="5" piece_type="Blade" mesh="AR_spear_blade_b" length="23.7" weight="0.250" excluded_item_usage_features="swing">
		<BladeData stack_amount="2" physics_material="wood_weapon" body_name="bo_spear_b" holster_mesh="no_jav_quiver" holster_body_name="bo_throwing_spear_quiver_5" holster_mesh_length="96.8">
			<Thrust damage_type="Pierce" damage_factor="1.5"/>
		</BladeData>
		<Flags>
			<Flag name="BonusAgainstShield"/>
		</Flags>
		<Materials>
			<Material id="Iron3" count="1"/>
		</Materials>
	</CraftingPiece>
	<CraftingPiece id="AR_spear_blade_c" name="{=osa_ar_spear_blade_c}Light Angon Head" tier="4" piece_type="Blade" mesh="AR_spear_blade_c" length="23.7" weight="0.250" excluded_item_usage_features="swing">
		<BladeData stack_amount="2" physics_material="wood_weapon" body_name="bo_spear_b" holster_mesh="no_jav_quiver" holster_body_name="bo_throwing_spear_quiver_1_1" holster_mesh_length="68.9">
			<Thrust damage_type="Pierce" damage_factor="1.2"/>
		</BladeData>
		<Flags>
			<Flag name="BonusAgainstShield"/>
		</Flags>
		<Materials>
			<Material id="Iron3" count="1"/>
		</Materials>
	</CraftingPiece>
	<CraftingPiece id="AR_spear_blade_d" name="{=osa_ar_spear_blade_d}Crude Wooden Spear Head" tier="1" piece_type="Blade" mesh="AR_spear_blade_d" length="22.862" weight="0.100" excluded_item_usage_features="swing">
		<BladeData stack_amount="5" physics_material="wood_weapon" body_name="bo_spear_b" holster_mesh="no_jav_quiver" holster_body_name="bo_throwing_spear_quiver_1_1" holster_mesh_length="68.9">
			<Thrust damage_type="Pierce" damage_factor="0.3" />
		</BladeData>
		<Materials>
			<Material id="Iron2" count="1" />
		</Materials>
	</CraftingPiece>
	<CraftingPiece id="spear_blade_35_blunt" name="{=ZUp9mm79}Jagged Spear Head" tier="5" piece_type="Blade" mesh="AR_spear_blade_35_blunt" length="41" weight="0.3256" excluded_item_usage_features="swing">
		<BladeData stack_amount="2" physics_material="wood_weapon" body_name="bo_spear_b" holster_mesh="no_jav_quiver" holster_body_name="bo_throwing_spear_quiver_5_1" holster_mesh_length="96.7">
			<Thrust damage_type="Pierce" damage_factor="1.1"/>
		</BladeData>
		<Flags>
		</Flags>
		<Materials>
			<Material id="Iron3" count="3"/>
		</Materials>
	</CraftingPiece>
	<CraftingPiece id="spear_blade_15_blunt" name="{=Y4tIQnS4}Short Simple Spear Head" tier="2" piece_type="Blade" mesh="AR_spear_blade_15_blunt" length="22.862" weight="0.100" excluded_item_usage_features="swing">
		<BladeData stack_amount="4" physics_material="wood_weapon" body_name="bo_spear_b" holster_mesh="no_jav_quiver" holster_body_name="bo_throwing_spear_quiver_1_1" holster_mesh_length="68.9">
			<Thrust damage_type="Pierce" damage_factor="0.8"/>
		</BladeData>
		<Materials>
			<Material id="Iron2" count="1"/>
		</Materials>
	</CraftingPiece>
	<CraftingPiece id="spear_blade_15_blunt" name="{=Y4tIQnS4}Short Simple Spear Head" tier="2" piece_type="Blade" mesh="AR_spear_blade_15_blunt" length="22.862" weight="0.100" excluded_item_usage_features="swing">
		<BladeData stack_amount="4" physics_material="wood_weapon" body_name="bo_spear_b" holster_mesh="no_jav_quiver" holster_body_name="bo_throwing_spear_quiver_1_1" holster_mesh_length="68.9">
			<Thrust damage_type="Pierce" damage_factor="0.8"/>
		</BladeData>
		<Materials>
			<Material id="Iron2" count="1"/>
		</Materials>
	</CraftingPiece>
	
	
</CraftingPieces>